pyexploitdb/__init__.py
pyexploitdb/cveToEdbid.json
pyexploitdb/edbidToCve.json
pyexploitdb-0.3.12.dist-info/licenses/LICENSE
pyexploitdb-0.3.12.dist-info/METADATA
pyexploitdb-0.3.12.dist-info/WHEEL
pyexploitdb-0.3.12.dist-info/top_level.txt
pyexploitdb-0.3.12.dist-info/RECORD
