Metadata-Version: 2.4
Name: pyexploitdb
Version: 0.3.12
Summary: An optimized Python3 library to fetch the most recent exploit-database,
Home-page: https://github.com/Hackman238/pyExploitDb
Author: Shane William Scott
Author-email: shane@shanewilliamscott.com
License: GPL-3.0-only
Project-URL: Source, https://github.com/Hackman238/pyExploitDb
Project-URL: Issue Tracker, https://github.com/Hackman238/pyExploitDb/issues
Classifier: Development Status :: 5 - Production/Stable
Classifier: Intended Audience :: Developers
Classifier: License :: OSI Approved :: GNU General Public License v3 (GPLv3)
Classifier: Programming Language :: Python :: 3 :: Only
Classifier: Programming Language :: Python :: 3.10
Classifier: Programming Language :: Python :: 3.11
Classifier: Programming Language :: Python :: 3.12
Classifier: Operating System :: OS Independent
Requires-Python: >=3.10
License-File: LICENSE
Requires-Dist: GitPython>=3.1
Requires-Dist: requests>=2.28
Dynamic: author
Dynamic: author-email
Dynamic: classifier
Dynamic: description
Dynamic: description-content-type
Dynamic: home-page
Dynamic: license
Dynamic: license-file
Dynamic: project-url
Dynamic: requires-dist
Dynamic: requires-python
Dynamic: summary
